{
  "projects": [
    {
      "title": "Project CI/CD",
      "description": "Implementación de pipelines CI/CD con GitHub Actions y Docker.",
      "image": "./images/projects/ci-cd.png",
      "githubLink": "https://github.com/usuario/ci-cd-project",
      "technologies": ["GitHub Actions", "Docker", "AWS"]
    },
    {
      "title": "Project Hexagonal Architecture",
      "description": "Backend desarrollado siguiendo principios de Clean Architecture.",
      "image": "./images/projects/hexagonal-architecture.png",
      "githubLink": "https://github.com/eduardoorm/clean-architecture",
      "technologies": ["Nest.js", "TypeScript"]
    },
    {
      "title": "Microservices - Firebase",
      "description": "Web app utilizando Firebase Authentication y Firestore.",
      "image": "./images/projects/microservice.jpeg",
      "githubLink": "https://github.com/eduardoorm/Recommendation-IA",
      "technologies": ["Firebase", "React", "CSS"]
    },
    {
      "title": "Project TypeScript",
      "description": "Aplicación frontend desarrollada completamente en TypeScript.",
      "image": "./images/projects/typescript.png",
      "githubLink": "https://github.com/usuario/typescript-project",
      "technologies": ["TypeScript", "React", "Vite"]
    },
    {
      "title": "Project Functional Programming",
      "description": "Ejercicios y proyectos enfocados en programación funcional.",
      "image": "./images/projects/programacion-funcional.png",
      "githubLink": "https://github.com/usuario/functional-programming",
      "technologies": ["JavaScript", "Ramda.js"]
    },
    {
      "title": "Project System Design",
      "description": "Documentación y diseño de sistemas escalables.",
      "image": "./images/projects/system_desing.png",
      "githubLink": "https://github.com/usuario/system-design",
      "technologies": ["System Design", "Arquitectura de Software"]
    },
    {
      "title": "Project Mongo DB",
      "description": "Proyecto de base de datos no relacional con MongoDB.",
      "image": "./images/projects/mongodb.png",
      "githubLink": "https://github.com/usuario/mongodb-project",
      "technologies": ["MongoDB", "Mongoose", "Node.js"]
    },
    {
      "title": "Project Docker",
      "description": "Contenerización de aplicaciones usando Docker y Docker Compose.",
      "image": "./images/projects/docker.jpg",
      "githubLink": "https://github.com/usuario/docker-project",
      "technologies": ["Docker", "Docker Compose"]
    },
    {
      "title": "Project Clean Code",
      "description": "Mejores prácticas de Clean Code aplicadas a proyectos reales.",
      "image": "./images/projects/clean-code.png",
      "githubLink": "https://github.com/usuario/clean-code",
      "technologies": ["Clean Code", "Refactorización"]
    },
    {
      "title": "Project Python",
      "description": "Scripts y proyectos utilizando Python 3.",
      "image": "./images/projects/python.png",
      "githubLink": "https://github.com/usuario/python-project",
      "technologies": ["Python", "Flask", "Pandas"]
    },
    {
      "title": "Project Azure",
      "description": "Servicios cloud desplegados en Google Cloud Platform.",
      "image": "./images/projects/azure.png",
      "githubLink": "https://github.com/usuario/gcp-project",
      "technologies": ["GCP", "Cloud Functions", "Firestore"]
    },
    {
      "title": "Project GraphQL",
      "description": "API construida con Apollo Server y GraphQL.",
      "image": "./images/projects/graphql.jpg",
      "githubLink": "https://github.com/usuario/graphql-project",
      "technologies": ["GraphQL", "Apollo Server", "Node.js"]
    }
    ,
    {
      "title": "Project GraphQL",
      "description": "API construida con Apollo Server y GraphQL.",
      "image": "./images/projects/graphql.jpg",
      "githubLink": "https://github.com/usuario/graphql-project",
      "technologies": ["GraphQL", "Apollo Server", "Node.js"]
    }
    ,
    {
      "title": "Project Apache Kafka",
      "description": "Sistema de mensajería distribuido utilizando Apache Kafka.",
      "image": "./images/projects/kafka.jpg",
      "githubLink": "https://github.com/usuario/graphql-project",
      "technologies": ["GraphQL", "Apollo Server", "Node.js"]
    }
    ,
    {
      "title": "Project Redis",
      "description": "Sistema de mensajería distribuido utilizando Redis.",
      "image": "./images/projects/redis.jpeg",
      "githubLink": "https://github.com/usuario/redis-project",
      "technologies": ["Redis", "Node.js"]
    },
    {
      "title": "Project Terraform",
      "description": "Sistema de mensajería distribuido utilizando Redis.",
      "image": "./images/projects/terraform.png",
      "githubLink": "https://github.com/usuario/redis-project",
      "technologies": ["Redis", "Node.js"]
    },
    {
      "title": "Google I/O - WebSite",
      "description": "Landing page responsive usando HTML, CSS y JavaScript puro.",
      "image": "./images/projects/web_io.png",
      "githubLink": "https://github.com/eduardoorm/googleIO-ica",
      "demoLink": "https://eduardoorm.github.io/googleIO-ica/",
      "technologies": ["React JS"] 
    },
    {
      "title": "Ecommerce - Website",
      "description": "Proyecto de ecommerce desarrollado con React",
      "image": "./images/projects/eccomerce_alura.png",
      "githubLink": "https://github.com/usuario/vue-webapp",
      "demoLink": "https://eduardoorm.github.io/Ecommerce-Challenge/",
      "technologies": ["HTML", "CSS", "JavaScript"]
    },
    {
      "title": "Compute Up - Website",
      "description": "API REST construida con Node.js y Express para CRUD de usuarios.",
      "image": "./images/projects/computeup.png",
      "githubLink": "https://github.com/eduardoorm/computerUp",
      "demoLink": "https://computeup.pe/",
      "technologies": ["Node.js", "Express", "MongoDB"]
    }
  ]
}
